{
  "__resolveType": "site/sections/Theme/Theme.tsx",
  "buttonStyle": {
    "--border-btn": "1px",
    "--rounded-btn": "2rem",
    "--btn-focus-scale": "0.9",
    "--animation-btn": "0.25s"
  },
  "font": {
    "__resolveType": "website/loaders/fonts/googleFonts.ts",
    "fonts": [
      {
        "variations": [],
        "family": "Albert Sans"
      }
    ]
  },
  "mainColors": {
    "base-100": "#030806",
    "primary": "#ffffff",
    "secondary": "#0A2121",
    "tertiary": "#02F67C",
    "neutral": "#162121"
  },
  "complementaryColors": {
    "base-200": "#ffffff",
    "base-content": "#ffffff",
    "base-300": "#C9CFCF",
    "tertiary-content": "#113032",
    "neutral-content": "#0D1717",
    "info-content": "#113032"
  }
}